[{"brewery":"Birrificio Abusivo","city":"San Marino","lat":43.93667,"long":12.44639,"best_beer":"Speak Easy","best_beer_score":2.8333333333,"most_popular_beer":"Illecita","popularity":1.0,"n_beers":5.0,"avg_abv":5.26,"max_abv":7.5},{"brewery":"Bar La Capanna","city":"San Marino","lat":43.93667,"long":12.44639,"best_beer":"La Capanna Birra Di San Marino","best_beer_score":3.1,"most_popular_beer":"La Capanna Birra Di San Marino","popularity":1.0,"n_beers":1.0,"avg_abv":5.0,"max_abv":5.0},{"brewery":"Birrifico Artigianale Sammarinese Srl","city":"Serravalle","lat":43.96897,"long":12.48167,"best_beer":"Titanbra\u00fc Pils","best_beer_score":3.155,"most_popular_beer":"Titanbra\u00fc Pils","popularity":2.0,"n_beers":5.0,"avg_abv":5.68,"max_abv":7.5}]